winzy_outlook_meetings/__init__.py
winzy_outlook_meetings/app.py
winzy_outlook_meetings-0.0.2.dist-info/licenses/LICENSE
winzy_outlook_meetings-0.0.2.dist-info/METADATA
winzy_outlook_meetings-0.0.2.dist-info/WHEEL
winzy_outlook_meetings-0.0.2.dist-info/entry_points.txt
winzy_outlook_meetings-0.0.2.dist-info/top_level.txt
winzy_outlook_meetings-0.0.2.dist-info/RECORD
