Metadata-Version: 2.4
Name: winzy-outlook-meetings
Version: 0.0.2
Summary: Get outlook calendar entries in commandline.
Author: Sukhbinder Singh
License: Apache-2.0
Project-URL: Homepage, https://github.com/sukhbinder/winzy-outlook-meetings
Project-URL: Changelog, https://github.com/sukhbinder/winzy-outlook-meetings/releases
Project-URL: Issues, https://github.com/sukhbinder/winzy-outlook-meetings/issues
Project-URL: CI, https://github.com/sukhbinder/winzy-outlook-meetings/actions
Classifier: License :: OSI Approved :: Apache Software License
License-File: LICENSE
Requires-Dist: winzy
Requires-Dist: dateutils
Provides-Extra: test
Requires-Dist: pytest; extra == "test"
Dynamic: license-file
